vemetric/__init__.py
vemetric/_version.py
vemetric/client.py
vemetric-0.2.0.dist-info/METADATA
vemetric-0.2.0.dist-info/WHEEL
vemetric-0.2.0.dist-info/licenses/LICENSE
vemetric-0.2.0.dist-info/RECORD
