Metadata-Version: 2.4
Name: vemetric
Version: 0.2.0
Summary: Official Python SDK for Vemetric
Project-URL: Homepage, https://vemetric.com
Project-URL: Source, https://github.com/vemetric/vemetric-python
Project-URL: Tracker, https://github.com/vemetric/vemetric-python/issues
Author-email: Vemetric <info@vemetric.com>
License: MIT
License-File: LICENSE
Requires-Python: >=3.9
Requires-Dist: requests>=2.27
Provides-Extra: test
Requires-Dist: pytest>=7.0; extra == 'test'
Requires-Dist: requests-mock>=1.11; extra == 'test'
